README.md
pyproject.toml
setup.py
img_detector_boxes_red/__init__.py
img_detector_boxes_red/model.py
img_detector_boxes_red.egg-info/PKG-INFO
img_detector_boxes_red.egg-info/SOURCES.txt
img_detector_boxes_red.egg-info/dependency_links.txt
img_detector_boxes_red.egg-info/requires.txt
img_detector_boxes_red.egg-info/top_level.txt
img_detector_boxes_red/analysis/__init__.py
img_detector_boxes_red/analysis/visualize.py
img_detector_boxes_red/data/__init__.py
img_detector_boxes_red/data/dataset.py
img_detector_boxes_red/data/transforms/__init__.py
img_detector_boxes_red/data/transforms/blur.py
img_detector_boxes_red/data/transforms/crop.py
img_detector_boxes_red/data/transforms/flip.py
img_detector_boxes_red/data/transforms/rescale.py
img_detector_boxes_red/data/transforms/rotate.py