Metadata-Version: 2.1
Name: img-detector-boxes-red
Version: 1.0.4
Summary: A model to detect images
Home-page: UNKNOWN
Author: Satvik Bansal
Author-email: satvik.bansal2001@gmail.com
License: GPLv3
Platform: UNKNOWN
Classifier: License :: OSI Approved :: GNU General Public License v3 (GPLv3)
Classifier: Programming Language :: Python :: 3
Classifier: Programming Language :: Python :: 3.8
